Metadata-Version: 2.1
Name: wslarkbot
Version: 0.2.4
Summary: lark(feishu) websocket client
Home-page: UNKNOWN
Author: lloydzhou@gmail..com
License: MIT
Project-URL: Documentation, https://www.connectai-e.com
Project-URL: Code, http://github.com/connectAI-E/Feishu-Webhook-Proxy
Project-URL: Issue tracker, http://github.com/connectAI-E/Feishu-Webhook-Proxy/issues
Keywords: Feishu,Lark,Webhook,Websocket,Bot
Platform: UNKNOWN
License-File: LICENSE
